[["achievements",{"version":2,"data":{"vecHighlight":[{"strID":"30","strName":"Agente Proficiente","strDescription":"Conclua a história principal no modo Intenso ou superior.","bAchieved":true,"rtUnlocked":1679780432,"strImage":"https://steamcdn-a.akamaihd.net/steamcommunity/public/images/apps/2050650/6ae33bd366d1f40365e00589719fd7cbf9f45b4a.jpg","bHidden":false,"flMinProgress":0,"flCurrentProgress":0,"flMaxProgress":0,"flAchieved":32.20000076293945},{"strID":"28","strName":"Agente Promissor","strDescription":"Conclua a história principal no modo Padrão ou superior.","bAchieved":true,"rtUnlocked":1679780431,"strImage":"https://steamcdn-a.akamaihd.net/steamcommunity/public/images/apps/2050650/8b15f89a9004ded0670378d4f8cbc873a17fa08f.jpg","bHidden":false,"flMinProgress":0,"flCurrentProgress":0,"flMaxProgress":0,"flAchieved":61.099998474121094},{"strID":"12","strName":"Você É Peixe Pequeno!","strDescription":"Derrote Osmund Saddler.","bAchieved":true,"rtUnlocked":1679779921,"strImage":"https://steamcdn-a.akamaihd.net/steamcommunity/public/images/apps/2050650/100bcde134514ce3a46a1c8f813f0cd665e930c3.jpg","bHidden":true,"flMinProgress":0,"flCurrentProgress":0,"flMaxProgress":0,"flAchieved":66.0999984741211},{"strID":"20","strName":"Fuga Suave","strDescription":"Fuja na moto aquática sem sofrer dano.","bAchieved":true,"rtUnlocked":1679779921,"strImage":"https://steamcdn-a.akamaihd.net/steamcommunity/public/images/apps/2050650/dc1e8e52533ddf0c7b91c5982956c0fb2e97e881.jpg","bHidden":false,"flMinProgress":0,"flCurrentProgress":0,"flMaxProgress":0,"flAchieved":24.100000381469727},{"strID":"11","strName":"Você Já Foi um Cara Legal","strDescription":"Derrote Jack Krauser.","bAchieved":true,"rtUnlocked":1679774413,"strImage":"https://steamcdn-a.akamaihd.net/steamcommunity/public/images/apps/2050650/6ee35145f69b77da3573351f23eeed5dd0dfaf99.jpg","bHidden":true,"flMinProgress":0,"flCurrentProgress":0,"flMaxProgress":0,"flAchieved":67.5},{"strID":"15","strName":"Dois Insetos com Uma Bala Só","strDescription":"Mate dois parasitas dentro de um Regenerador com uma bala só.","bAchieved":true,"rtUnlocked":1679769710,"strImage":"https://steamcdn-a.akamaihd.net/steamcommunity/public/images/apps/2050650/f47551e71ccd2e81246f24928df25536688e0799.jpg","bHidden":false,"flMinProgress":0,"flCurrentProgress":0,"flMaxProgress":0,"flAchieved":44.20000076293945},{"strID":"3","strName":"Obra-Prima","strDescription":"Obtenha a melhoria exclusiva de uma arma.","bAchieved":true,"rtUnlocked":1679768221,"strImage":"https://steamcdn-a.akamaihd.net/steamcommunity/public/images/apps/2050650/84539c24d82f190d8a7145fb7af223d1201571d7.jpg","bHidden":false,"flMinProgress":0,"flCurrentProgress":0,"flMaxProgress":0,"flAchieved":60.79999923706055},{"strID":"10","strName":"Não, Valeu!","strDescription":"Derrote Ramón Salazar.","bAchieved":true,"rtUnlocked":1679763038,"strImage":"https://steamcdn-a.akamaihd.net/steamcommunity/public/images/apps/2050650/09a2da5eafd99bd5ccaf8f607c3c4a1ca8b51879.jpg","bHidden":true,"flMinProgress":0,"flCurrentProgress":0,"flMaxProgress":0,"flAchieved":71.19999694824219},{"strID":"9","strName":"Dê Tchauzinho, Mão Direita","strDescription":"Derrote o Verdugo.","bAchieved":true,"rtUnlocked":1679755215,"strImage":"https://steamcdn-a.akamaihd.net/steamcommunity/public/images/apps/2050650/07cf575e8a3a7af518c13c1e5d5f4549335356bf.jpg","bHidden":true,"flMinProgress":0,"flCurrentProgress":0,"flMaxProgress":0,"flAchieved":48.29999923706055},{"strID":"21","strName":"Avaliação Astuta","strDescription":"Venda um único tesouro por pelo menos 100000 ptas.","bAchieved":true,"rtUnlocked":1679754476,"strImage":"https://steamcdn-a.akamaihd.net/steamcommunity/public/images/apps/2050650/f104d8b98dcc0a6a0b60a1a05cece4780ec7c6d1.jpg","bHidden":false,"flMinProgress":0,"flCurrentProgress":0,"flMaxProgress":0,"flAchieved":46.099998474121094},{"strID":"17","strName":"Exagerado","strDescription":"Use um canhão para derrotar um fanático.","bAchieved":true,"rtUnlocked":1679693430,"strImage":"https://steamcdn-a.akamaihd.net/steamcommunity/public/images/apps/2050650/3f2e31ef9e8aa870f6a9422901224934065a7ca2.jpg","bHidden":false,"flMinProgress":0,"flCurrentProgress":0,"flMaxProgress":0,"flAchieved":72.19999694824219},{"strID":"8","strName":"Chefão no Chão","strDescription":"Derrote Bitores Méndez.","bAchieved":true,"rtUnlocked":1679691904,"strImage":"https://steamcdn-a.akamaihd.net/steamcommunity/public/images/apps/2050650/af1379dad0e6400366e3fb477e734c22622eeff4.jpg","bHidden":true,"flMinProgress":0,"flCurrentProgress":0,"flMaxProgress":0,"flAchieved":80.80000305175781}],"vecUnachieved":[{"strID":"39","strName":"Mandou Bem","strDescription":"Destrua 5 alvos na galeria de tiro com um disparo.","strImage":"https://steamcdn-a.akamaihd.net/steamcommunity/public/images/apps/2050650/70bc91916cb338746c9ae4e65431bec2e43a3f8c.jpg","bAchieved":false,"rtUnlocked":0,"flAchieved":25.399999618530273,"flMinProgress":0,"flCurrentProgress":0,"flMaxProgress":0},{"strID":"18","strName":"Proteção de Propriedade","strDescription":"Passe de ambos os segmentos nos carrinhos no túnel subterrâneo sem sofrer dano.","strImage":"https://steamcdn-a.akamaihd.net/steamcommunity/public/images/apps/2050650/c0d39ac30d83daef8ba3ece79ab022a53706c007.jpg","bAchieved":false,"rtUnlocked":0,"flAchieved":24.700000762939453,"flMinProgress":0,"flCurrentProgress":0,"flMaxProgress":0},{"strID":"24","strName":"Invasor","strDescription":"Obtenha todos os tesouros do mapa do tesouro da ilha em uma única jogada.","strImage":"https://steamcdn-a.akamaihd.net/steamcommunity/public/images/apps/2050650/b8b04451a2f425dc124295648cd5ab129ce5e734.jpg","bAchieved":false,"rtUnlocked":0,"flAchieved":23.299999237060547,"flMinProgress":0,"flCurrentProgress":0,"flMaxProgress":0},{"strID":"33","strName":"Maratonista","strDescription":"Conclua a história principal em 8 horas.","strImage":"https://steamcdn-a.akamaihd.net/steamcommunity/public/images/apps/2050650/715fcbe8b71b2893dafdd0dfa50695404125f134.jpg","bAchieved":false,"rtUnlocked":0,"flAchieved":21.899999618530273,"flMinProgress":0,"flCurrentProgress":0,"flMaxProgress":0},{"strID":"26","strName":"Pau Para Toda Obra","strDescription":"Conclua todos os pedidos do Mercador.","strImage":"https://steamcdn-a.akamaihd.net/steamcommunity/public/images/apps/2050650/e080280b101315c080b0679d1026c60a27605ceb.jpg","bAchieved":false,"rtUnlocked":0,"flAchieved":21.600000381469727,"flMinProgress":0,"flCurrentProgress":0,"flMaxProgress":0},{"strID":"27","strName":"Desenrolar da Revolução","strDescription":"Destrua todos os Castelões Mecânicos.","strImage":"https://steamcdn-a.akamaihd.net/steamcommunity/public/images/apps/2050650/f9e744aae383421a45869c320d3a76a8bbf02721.jpg","bAchieved":false,"rtUnlocked":0,"flAchieved":18.200000762939453,"flMinProgress":0,"flCurrentProgress":0,"flMaxProgress":0},{"strID":"22","strName":"Bandido","strDescription":"Obtenha todos os tesouros do mapa do tesouro do vilarejo em uma única jogada.","strImage":"https://steamcdn-a.akamaihd.net/steamcommunity/public/images/apps/2050650/897e475dc990d9de85e63c332a343c2ac0550811.jpg","bAchieved":false,"rtUnlocked":0,"flAchieved":18.100000381469727,"flMinProgress":0,"flCurrentProgress":0,"flMaxProgress":0},{"strID":"19","strName":"Respeitando o Limite de Peso","strDescription":"Chegue ao topo da torre do relógio sem o elevador parar nem uma vez.","strImage":"https://steamcdn-a.akamaihd.net/steamcommunity/public/images/apps/2050650/63eb92a8a04a42a2a738590d9ae6b649d3d6efc8.jpg","bAchieved":false,"rtUnlocked":0,"flAchieved":17,"flMinProgress":0,"flCurrentProgress":0,"flMaxProgress":0},{"strID":"14","strName":"Nem Ouviu Chegando","strDescription":"Derrote um Garrador usando apenas facas.","strImage":"https://steamcdn-a.akamaihd.net/steamcommunity/public/images/apps/2050650/09679d549bac097acf3e72c88928920606448b66.jpg","bAchieved":false,"rtUnlocked":0,"flAchieved":16.799999237060547,"flMinProgress":0,"flCurrentProgress":0,"flMaxProgress":0},{"strID":"38","strName":"Mira Imbatível","strDescription":"Obtenha nota S em todos os jogos na galeria de tiro.","strImage":"https://steamcdn-a.akamaihd.net/steamcommunity/public/images/apps/2050650/99d7baf084127c97033686f4f12af342b870b1ef.jpg","bAchieved":false,"rtUnlocked":0,"flAchieved":15.399999618530273,"flMinProgress":0,"flCurrentProgress":0,"flMaxProgress":0},{"strID":"23","strName":"Assaltante","strDescription":"Obtenha todos os tesouros do mapa do tesouro do castelo em uma única jogada.","strImage":"https://steamcdn-a.akamaihd.net/steamcommunity/public/images/apps/2050650/74dc5c4a1a30b3e7ab61b7474aed493f6a9f6ae2.jpg","bAchieved":false,"rtUnlocked":0,"flAchieved":12.899999618530273,"flMinProgress":0,"flCurrentProgress":0,"flMaxProgress":0},{"strID":"31","strName":"Investigador Classe S+","strDescription":"Conclua a história principal no modo Intenso com nota S+.","strImage":"https://steamcdn-a.akamaihd.net/steamcommunity/public/images/apps/2050650/58ce8151ee6de92ce824bc1301620f48a9b9162d.jpg","bAchieved":false,"rtUnlocked":0,"flAchieved":11.100000381469727,"flMinProgress":0,"flCurrentProgress":0,"flMaxProgress":0}],"vecAchievedHidden":[{"strID":"10","strName":"Não, Valeu!","strDescription":"Derrote Ramón Salazar.","strImage":"https://steamcdn-a.akamaihd.net/steamcommunity/public/images/apps/2050650/09a2da5eafd99bd5ccaf8f607c3c4a1ca8b51879.jpg","bAchieved":true,"rtUnlocked":1679763038,"flAchieved":0},{"strID":"11","strName":"Você Já Foi um Cara Legal","strDescription":"Derrote Jack Krauser.","strImage":"https://steamcdn-a.akamaihd.net/steamcommunity/public/images/apps/2050650/6ee35145f69b77da3573351f23eeed5dd0dfaf99.jpg","bAchieved":true,"rtUnlocked":1679774413,"flAchieved":0},{"strID":"12","strName":"Você É Peixe Pequeno!","strDescription":"Derrote Osmund Saddler.","strImage":"https://steamcdn-a.akamaihd.net/steamcommunity/public/images/apps/2050650/100bcde134514ce3a46a1c8f813f0cd665e930c3.jpg","bAchieved":true,"rtUnlocked":1679779921,"flAchieved":0},{"strID":"7","strName":"Lança-Arpão","strDescription":"Derrote Del Lago.","strImage":"https://steamcdn-a.akamaihd.net/steamcommunity/public/images/apps/2050650/af8cd4754665d93581c214709288dee50383adee.jpg","bAchieved":true,"rtUnlocked":1679677634,"flAchieved":0},{"strID":"8","strName":"Chefão no Chão","strDescription":"Derrote Bitores Méndez.","strImage":"https://steamcdn-a.akamaihd.net/steamcommunity/public/images/apps/2050650/af1379dad0e6400366e3fb477e734c22622eeff4.jpg","bAchieved":true,"rtUnlocked":1679691904,"flAchieved":0},{"strID":"9","strName":"Dê Tchauzinho, Mão Direita","strDescription":"Derrote o Verdugo.","strImage":"https://steamcdn-a.akamaihd.net/steamcommunity/public/images/apps/2050650/07cf575e8a3a7af518c13c1e5d5f4549335356bf.jpg","bAchieved":true,"rtUnlocked":1679755215,"flAchieved":0}],"nTotal":39,"nAchieved":20}}],["badge",{"version":1,"data":{"dtNextRetry":null,"strName":"Rubi","strIconURL":"https://cdn.akamai.steamstatic.com/steamcommunity/public/images/items/2050650/27a49b5b41a58c3452d253e2346db4363dc98061.png","nLevel":1,"nMaxLevel":5,"nXP":100,"bMaxed":null,"strNextLevelName":"Jarro","nNextLevelXP":200,"rgCards":[{"strName":"Leon S. Kennedy","strTitle":"Leon S. Kennedy","strImgURL":"https://community.akamai.steamstatic.com/economy/image/IzMF03bk9WpSBq-S-ekoE33L-iLqGFHVaU25ZzQNQcXdA3g5gMEPvUZZEfSLO6FSSMAouGvDXJfBjI0CxnMJmDgDemTs1GBhYLhAPcTIiza16smIEnrybC6CJizYG1s1H7dZZGyKqmWh4--XSm6fQu4kRw4ELKAG-jJKacCBahA-gI4C-GS9lgptEBFucMpUdAqp9X0eMLoglSNBJJ4EyiX1JJOKjVs3OUE5Xb7iBejBO4ijlistDh9mHadLMdmQvXDyuMmmfLGLL0FqM9N8","strArtworkURL":"https://cdn.akamai.steamstatic.com/steamcommunity/public/images/items/2050650/5a011883b3eb9f28a52743c0b795a0d72c3e9ad7.jpg","strMarketHash":"2050650-Leon S. Kennedy","nOwned":1},{"strName":"Ashley Graham","strTitle":"Ashley Graham","strImgURL":"https://community.akamai.steamstatic.com/economy/image/IzMF03bk9WpSBq-S-ekoE33L-iLqGFHVaU25ZzQNQcXdA3g5gMEPvUZZEfSLO6FSSMAouGvDXJfBjI0CxnMJmDgDemTs1GBhYLhNK8PKxRywhvCMFHX6Lj7JLibcQQtpTrsKZ26N-mCktOiVQj3MQLkkRAAMdfRW9TFMb8-PNhJv3NEO_TP2h0p6WBQnYMFDYjCyx3UUNOAnmyBHI8hTnCb3dZzd0A5lO0FsX-uzVejLaYehmXwhXBhgTvVIYY7ApmWyr4G3Z_UfW1Nyyw","strArtworkURL":"https://cdn.akamai.steamstatic.com/steamcommunity/public/images/items/2050650/7ba126a6d91c12dacef61c9819de7e71f8fb881a.jpg","strMarketHash":"2050650-Ashley Graham","nOwned":0},{"strName":"Luis Serra Navarro","strTitle":"Luis Serra Navarro","strImgURL":"https://community.akamai.steamstatic.com/economy/image/IzMF03bk9WpSBq-S-ekoE33L-iLqGFHVaU25ZzQNQcXdA3g5gMEPvUZZEfSMJ6dESN8p_2SVTY7V2NsPwXMKnT4QPivs0XEwSfBlK4D1xRfpoKmjHWL2eiXLaSjUHVltQOZfPWCIqzSs4OmUS2vBSektQQwHfqQD8mwYPcqIOBo63Y9e8zPvxhwzDhgvNMdJYgu-2EsaPLwizXwQdspXz3fxI5be1ldmPRdtCb_hU--WbNWslikgVEliHqIdNd7HvSC55tevPeHAIPrO-PvDKQ","strArtworkURL":"https://cdn.akamai.steamstatic.com/steamcommunity/public/images/items/2050650/45fae86dfa091283b8a07b2a6a74d6951716387a.jpg","strMarketHash":"2050650-Luis Serra Navarro","nOwned":0},{"strName":"Ada Wong","strTitle":"Ada Wong","strImgURL":"https://community.akamai.steamstatic.com/economy/image/IzMF03bk9WpSBq-S-ekoE33L-iLqGFHVaU25ZzQNQcXdA3g5gMEPvUZZEfSLO6FSSMAouGvDXJfBjI0CxnMJmDgDemTs1GBhYLhNPMqN9wr1pqSEEXXwbWrFfyCKGA8wSOFcNWqIrzSl7bvHRGvMSL1-Sl0HK_MDpmZONcDdbRVrysdVrCO6mFZ5GwQXe8hHdwrmyCcSZLsmmXRAcshanXGhIcfeg1oxPEU-U77hUrWRaoCnl35xDx9iSr5aOtyD_ijuhgCaBS4","strArtworkURL":"https://cdn.akamai.steamstatic.com/steamcommunity/public/images/items/2050650/c67fad9e55142c1cd0a16d7347f88cebbfc578d8.jpg","strMarketHash":"2050650-Ada Wong","nOwned":0},{"strName":"Ingrid Hunnigan","strTitle":"Ingrid Hunnigan","strImgURL":"https://community.akamai.steamstatic.com/economy/image/IzMF03bk9WpSBq-S-ekoE33L-iLqGFHVaU25ZzQNQcXdA3g5gMEPvUZZEfSLO6FSSMAouGvDXJfBjI0CxnMJmDgDemTs1GBhYLhFNszUyQGwifeDEn3waTmCJizYG1s1GOVeZmnQqDfw4uTHSjGcQuAkQA9WKPQA8zBNOMiOakdo1YcPrTHuwgptEBFucMpUdAqp9X0eMLoglSNBJJ4EyiX1JJOKjVs3OUE5Xb7iBejBO4ijlistDh9mHadLMdmQvXDyuMmmfLGLL0i3Kl75","strArtworkURL":"https://cdn.akamai.steamstatic.com/steamcommunity/public/images/items/2050650/0f6629d51cbd3ab61dcf0e5c3850efbb5815a9b9.jpg","strMarketHash":"2050650-Ingrid Hunnigan","nOwned":0},{"strName":"Merchant","strTitle":"Mercador","strImgURL":"https://community.akamai.steamstatic.com/economy/image/IzMF03bk9WpSBq-S-ekoE33L-iLqGFHVaU25ZzQNQcXdA3g5gMEPvUZZEfSLO6FSSMAouGvDXJfBjI0CxnMJmDgDemTs1GBhYLhBPdnFwQH0s6SEEXXwbWqSeCCPGlxsGedXMm3f_zP05uyURDqaQb54EQoGLPFS-jFMa8zcPxdpysdVrCO6mFZ5GwQXe8hHdwrmyCcSZLsmmXRAcshanXGhIcfeg1oxPEU-U77hUrWRaoCnl35xDx9iSr5aOtyD_ijulhX4PXU","strArtworkURL":"https://cdn.akamai.steamstatic.com/steamcommunity/public/images/items/2050650/90dd7c0d2b3180954cb9d1e1e3e359e5abdb571c.jpg","strMarketHash":"2050650-Merchant (Trading Card)","nOwned":0},{"strName":"Bitores Méndez","strTitle":"Bitores Méndez","strImgURL":"https://community.akamai.steamstatic.com/economy/image/IzMF03bk9WpSBq-S-ekoE33L-iLqGFHVaU25ZzQNQcXdA3g5gMEPvUZZEfSLO6FSSMAouGvDXJfBjI0CxnMJmDgDemTs1GBhYLhOMd_J0gDo6s_IPyeySW7KKyTDWldlHOQLOGCM_Dai4unHQjGYFekqFQBSKaAA92UaacvaPxdr1oBarTXpxhMlTUFmYstBNg202HAWI4IsxSAVIJYAmnX1cMfYgF1lO05uD-ngBbvEatLxk3stWxxjFvMfZYmS6XC-_ZKkdLfYeu5xafMOV9WzRw","strArtworkURL":"https://cdn.akamai.steamstatic.com/steamcommunity/public/images/items/2050650/f783357538eef3a6ab2fd02b2fc0e49f9c638598.jpg","strMarketHash":"2050650-Bitores Méndez","nOwned":0},{"strName":"Ramón Salazar","strTitle":"Ramón Salazar","strImgURL":"https://community.akamai.steamstatic.com/economy/image/IzMF03bk9WpSBq-S-ekoE33L-iLqGFHVaU25ZzQNQcXdA3g5gMEPvUZZEfSLO6FSSMAouGvDXJfBjI0CxnMJmDgDemTs1GBhYLheOcaD41a-g7GDV0f2ZDbeLjOfFVNpGuZTZzzd_Tf3sOydQD7LErwsFw9XL6MH9mAbbJ2KOhU93YADqGDpkUclRlg4fMIAcgCpznEBDrQoySYXeMlRyCGmdZXch1gxYEI_C7-0UbrHPNWmxCYiWx5uTKUbZozE7Xfp_cLvKqnRO746Zvcv3XoN","strArtworkURL":"https://cdn.akamai.steamstatic.com/steamcommunity/public/images/items/2050650/592d0fb12ef518a97f2245d60564f76585b342b1.jpg","strMarketHash":"2050650-Ramón Salazar","nOwned":0},{"strName":"Jack Krauser","strTitle":"Jack Krauser","strImgURL":"https://community.akamai.steamstatic.com/economy/image/IzMF03bk9WpSBq-S-ekoE33L-iLqGFHVaU25ZzQNQcXdA3g5gMEPvUZZEfSLO6FSSMAouGvDXJfBjI0CxnMJmDgDemTs1GBhYLhGOcjNiy7poPeeGWaxYTrFKCSESgppSeZZMGqM-mWt5L-QRz3NE-kqQl9XfKAB9mNINZyLaxY10I4N-iuomUM7HBk6dsBUTwa2y3MWbL92yXQUJppXmyOjLpCM1Fgxb0BvCezkArXEaYWswyolXx02SvIfYd6L-Hu77tH8aOfF7Ml-","strArtworkURL":"https://cdn.akamai.steamstatic.com/steamcommunity/public/images/items/2050650/5e0d62fceb0605e9b31dc696333ffc2fc6286e9b.jpg","strMarketHash":"2050650-Jack Krauser","nOwned":0},{"strName":"Osmund Saddler","strTitle":"Osmund Saddler","strImgURL":"https://community.akamai.steamstatic.com/economy/image/IzMF03bk9WpSBq-S-ekoE33L-iLqGFHVaU25ZzQNQcXdA3g5gMEPvUZZEfSLO6FSSMAouGvDXJfBjI0CxnMJmDgDemTs1GBhYLhDK8bTzgGwkuOJGHjyenHNIiDeGQNtHrFWNWyK-mCntLiUF2vPEOF9EV1Re_RXpGxBNZjdbEQ53YcI8mbv2VRzGVAqfddCdR2Ew3kSNrh4ynITcM0BmCHyIcfRgQozbxVtXL20Ar-WZoejlCZ3WBtlGPFPNo6Q7TuspsDnLPqEfSv1b_I","strArtworkURL":"https://cdn.akamai.steamstatic.com/steamcommunity/public/images/items/2050650/9e885fab1503b5ea0ce6b896ad1972e41164d213.jpg","strMarketHash":"2050650-Osmund Saddler","nOwned":2}]}}],["friends",{"version":1,"data":{"your_info":{"minutes_played_forever":2689,"owned":true},"in_game":[],"played_recently":[{"steamid":"76561198815716149","minutes_played":5,"minutes_played_forever":2119}],"played_ever":[],"owns":[],"in_wishlist":[{"steamid":"76561198169040839"},{"steamid":"76561198834454177"}]}}],["achievementmap",{"version":4,"data":"[[2050650,[[\"28\",{\"strName\":\"Agente Promissor\",\"strDescription\":\"Conclua a história principal no modo Padrão ou superior.\",\"strImage\":\"https://steamcdn-a.akamaihd.net/steamcommunity/public/images/apps/2050650/8b15f89a9004ded0670378d4f8cbc873a17fa08f.jpg\",\"bAchieved\":true,\"flAchieved\":61.70000076293945}],[\"12\",{\"strName\":\"Você É Peixe Pequeno!\",\"strDescription\":\"Derrote Osmund Saddler.\",\"strImage\":\"https://steamcdn-a.akamaihd.net/steamcommunity/public/images/apps/2050650/100bcde134514ce3a46a1c8f813f0cd665e930c3.jpg\",\"bAchieved\":true,\"flAchieved\":66.80000305175781,\"bHidden\":true}],[\"11\",{\"strName\":\"Você Já Foi um Cara Legal\",\"strDescription\":\"Derrote Jack Krauser.\",\"strImage\":\"https://steamcdn-a.akamaihd.net/steamcommunity/public/images/apps/2050650/6ee35145f69b77da3573351f23eeed5dd0dfaf99.jpg\",\"bAchieved\":true,\"flAchieved\":68.19999694824219,\"bHidden\":true}],[\"21\",{\"strName\":\"Avaliação Astuta\",\"strDescription\":\"Venda um único tesouro por pelo menos 100000 ptas.\",\"strImage\":\"https://steamcdn-a.akamaihd.net/steamcommunity/public/images/apps/2050650/f104d8b98dcc0a6a0b60a1a05cece4780ec7c6d1.jpg\",\"bAchieved\":true,\"flAchieved\":46.400001525878906}],[\"10\",{\"strName\":\"Não, Valeu!\",\"strDescription\":\"Derrote Ramón Salazar.\",\"strImage\":\"https://steamcdn-a.akamaihd.net/steamcommunity/public/images/apps/2050650/09a2da5eafd99bd5ccaf8f607c3c4a1ca8b51879.jpg\",\"bAchieved\":true,\"flAchieved\":71.80000305175781,\"bHidden\":true}],[\"9\",{\"strName\":\"Dê Tchauzinho, Mão Direita\",\"strDescription\":\"Derrote o Verdugo.\",\"strImage\":\"https://steamcdn-a.akamaihd.net/steamcommunity/public/images/apps/2050650/07cf575e8a3a7af518c13c1e5d5f4549335356bf.jpg\",\"bAchieved\":true,\"flAchieved\":48.599998474121094,\"bHidden\":true}],[\"37\",{\"strName\":\"Atirador Amador\",\"strDescription\":\"Conclua um jogo na galeria de tiro.\",\"strImage\":\"https://steamcdn-a.akamaihd.net/steamcommunity/public/images/apps/2050650/63a90511999463da04fdba6abc6f807c98e96987.jpg\",\"bAchieved\":true,\"flAchieved\":82.4000015258789}],[\"17\",{\"strName\":\"Exagerado\",\"strDescription\":\"Use um canhão para derrotar um fanático.\",\"strImage\":\"https://steamcdn-a.akamaihd.net/steamcommunity/public/images/apps/2050650/3f2e31ef9e8aa870f6a9422901224934065a7ca2.jpg\",\"bAchieved\":true,\"flAchieved\":72.5}],[\"8\",{\"strName\":\"Chefão no Chão\",\"strDescription\":\"Derrote Bitores Méndez.\",\"strImage\":\"https://steamcdn-a.akamaihd.net/steamcommunity/public/images/apps/2050650/af1379dad0e6400366e3fb477e734c22622eeff4.jpg\",\"bAchieved\":true,\"flAchieved\":81,\"bHidden\":true}],[\"5\",{\"strName\":\"Uma Experiência de Quase Morte\",\"strDescription\":\"Resgate Ashley enquanto ela é levada por um inimigo.\",\"strImage\":\"https://steamcdn-a.akamaihd.net/steamcommunity/public/images/apps/2050650/33ce364d576c87e43f816848e577b794159efff5.jpg\",\"bAchieved\":true,\"flAchieved\":82.5999984741211}],[\"13\",{\"strName\":\"Tapem os Olhos\",\"strDescription\":\"Derrote 3 inimigos juntos com uma granada de atordoamento.\",\"strImage\":\"https://steamcdn-a.akamaihd.net/steamcommunity/public/images/apps/2050650/9f0afa8057595b34574919f47356059f3991a030.jpg\",\"bAchieved\":true,\"flAchieved\":59}],[\"7\",{\"strName\":\"Lança-Arpão\",\"strDescription\":\"Derrote Del Lago.\",\"strImage\":\"https://steamcdn-a.akamaihd.net/steamcommunity/public/images/apps/2050650/af8cd4754665d93581c214709288dee50383adee.jpg\",\"bAchieved\":true,\"flAchieved\":86.19999694824219,\"bHidden\":true}],[\"1\",{\"strName\":\"Faca Para Principiantes\",\"strDescription\":\"Apare um inimigo com uma faca.\",\"strImage\":\"https://steamcdn-a.akamaihd.net/steamcommunity/public/images/apps/2050650/57ed9194d804ddd7c5dd753c046870a9a0f58fb1.jpg\",\"bAchieved\":true,\"flAchieved\":91.69999694824219}],[\"2\",{\"strName\":\"Minha Peça Preferida\",\"strDescription\":\"Melhore uma arma.\",\"strImage\":\"https://steamcdn-a.akamaihd.net/steamcommunity/public/images/apps/2050650/a0247551f9d53b3a9aa66f5ee41661177c6ccef9.jpg\",\"bAchieved\":true,\"flAchieved\":89.80000305175781}],[\"4\",{\"strName\":\"Boa, Estranho!\",\"strDescription\":\"Conclua um pedido do Mercador.\",\"strImage\":\"https://steamcdn-a.akamaihd.net/steamcommunity/public/images/apps/2050650/1c8fc9f7efd2f055909f8df463c3e5356978419d.jpg\",\"bAchieved\":true,\"flAchieved\":88.5999984741211}],[\"6\",{\"strName\":\"Revolta Contra os Revoltantes\",\"strDescription\":\"Destrua um Castelão Mecânico.\",\"strImage\":\"https://steamcdn-a.akamaihd.net/steamcommunity/public/images/apps/2050650/dc0343d892ab6efddd0bfa37a5f9eb55e9b8e015.jpg\",\"bAchieved\":true,\"flAchieved\":81.19999694824219}],[\"20\",{\"strName\":\"Fuga Suave\",\"strDescription\":\"Fuja na moto aquática sem sofrer dano.\",\"strImage\":\"https://steamcdn-a.akamaihd.net/steamcommunity/public/images/apps/2050650/dc1e8e52533ddf0c7b91c5982956c0fb2e97e881.jpg\",\"bAchieved\":true,\"flAchieved\":24.5}],[\"30\",{\"strName\":\"Agente Proficiente\",\"strDescription\":\"Conclua a história principal no modo Intenso ou superior.\",\"strImage\":\"https://steamcdn-a.akamaihd.net/steamcommunity/public/images/apps/2050650/6ae33bd366d1f40365e00589719fd7cbf9f45b4a.jpg\",\"bAchieved\":true,\"flAchieved\":32.599998474121094}],[\"3\",{\"strName\":\"Obra-Prima\",\"strDescription\":\"Obtenha a melhoria exclusiva de uma arma.\",\"strImage\":\"https://steamcdn-a.akamaihd.net/steamcommunity/public/images/apps/2050650/84539c24d82f190d8a7145fb7af223d1201571d7.jpg\",\"bAchieved\":true,\"flAchieved\":61.29999923706055}],[\"15\",{\"strName\":\"Dois Insetos com Uma Bala Só\",\"strDescription\":\"Mate dois parasitas dentro de um Regenerador com uma bala só.\",\"strImage\":\"https://steamcdn-a.akamaihd.net/steamcommunity/public/images/apps/2050650/f47551e71ccd2e81246f24928df25536688e0799.jpg\",\"bAchieved\":true,\"flAchieved\":44.599998474121094}]]]]"}],["usernews",{"version":4,"data":["CAIQu++cogYZNSP9MgEAEAEhAAAAAAAAAAApWkofAAAAAABCAjI4","CAIQ5OWcogYZNSP9MgEAEAEhAAAAAAAAAAApWkofAAAAAABCAjEy","CAIQnfn3oQYZNSP9MgEAEAEhAAAAAAAAAAApWkofAAAAAABCAjEx","CAIQ18D3oQYZNSP9MgEAEAEhAAAAAAAAAAApWkofAAAAAABCAjIx","CAIQvZDdoQYZNSP9MgEAEAEhAAAAAAAAAAApWkofAAAAAABCAjEw","CAIQ/PPSoQYZNSP9MgEAEAEhAAAAAAAAAAApWkofAAAAAABCATk=","CAIQ5JipoQYZrATTPwEAEAEhAAAAAAAAAAApWkofAAAAAABCAjEw","CAIQ8JmooQYZrATTPwEAEAEhAAAAAAAAAAApWkofAAAAAABCAjM3","CAIQ0cmeoQYZNSP9MgEAEAEhAAAAAAAAAAApWkofAAAAAABCAjE3","CAIQpLaeoQYZNSP9MgEAEAEhAAAAAAAAAAApWkofAAAAAABCATg=","CAIQ3pWeoQYZNSP9MgEAEAEhAAAAAAAAAAApWkofAAAAAABCATU=","CAIQ5LKZoQYZrATTPwEAEAEhAAAAAAAAAAApWkofAAAAAABCAThCAjEzQgIxNw==","CAIQo8WUoQYZrATTPwEAEAEhAAAAAAAAAAApWkofAAAAAABCATU=","CAIQxcCToQYZNSP9MgEAEAEhAAAAAAAAAAApWkofAAAAAABCATc=","CAIQwpuToQYZNSP9MgEAEAEhAAAAAAAAAAApWkofAAAAAABCAjM3","CAIQ6pKToQYZNSP9MgEAEAEhAAAAAAAAAAApWkofAAAAAABCAjEz","CAIQ74P/oAYZrATTPwEAEAEhAAAAAAAAAAApWkofAAAAAABCATFCATJCATRCATZCATc=","CAIQ0dD9oAYZdWuVMwEAEAEhAAAAAAAAAAApWkofAAAAAABCAjEyQgIyMEICMjhCAjMw","CAIQzaX9oAYZdWuVMwEAEAEhAAAAAAAAAAApWkofAAAAAABCAjEx","CAIQnfX8oAYZdWuVMwEAEAEhAAAAAAAAAAApWkofAAAAAABCATNCAjE1","CAIQ3sz8oAYZdWuVMwEAEAEhAAAAAAAAAAApWkofAAAAAABCAjEw","CAIQ7In8oAYZdWuVMwEAEAEhAAAAAAAAAAApWkofAAAAAABCATlCAjIx","CAIQgbz5oAYZNSP9MgEAEAEhAAAAAAAAAAApWkofAAAAAABCATY=","CAIQrKD5oAYZNSP9MgEAEAEhAAAAAAAAAAApWkofAAAAAABCATJCATQ=","CAIQju/4oAYZNSP9MgEAEAEhAAAAAAAAAAApWkofAAAAAABCATE=","CB4QiMf4oAYZNSP9MgEAEAEhAAAAAAAAAAApWkofAAAAAAA=","CB4Qjrv4oAYZrATTPwEAEAEhAAAAAAAAAAApWkofAAAAAAA=","CAIQgKH4oAYZdWuVMwEAEAEhAAAAAAAAAAApWkofAAAAAABCAThCAjE3","CAIQht73oAYZdWuVMwEAEAEhAAAAAAAAAAApWkofAAAAAABCATU=","CAIQwrH3oAYZdWuVMwEAEAEhAAAAAAAAAAApWkofAAAAAABCATc=","CAIQlJn3oAYZdWuVMwEAEAEhAAAAAAAAAAApWkofAAAAAABCAjM3","CAIQ95L3oAYZdWuVMwEAEAEhAAAAAAAAAAApWkofAAAAAABCAjEz","CAIQk4f3oAYZdWuVMwEAEAEhAAAAAAAAAAApWkofAAAAAABCATI=","CAIQ5ef2oAYZdWuVMwEAEAEhAAAAAAAAAAApWkofAAAAAABCATY=","CAIQ1c/2oAYZdWuVMwEAEAEhAAAAAAAAAAApWkofAAAAAABCATFCATQ=","CB4QpqH2oAYZdWuVMwEAEAEhAAAAAAAAAAApWkofAAAAAAA=","COoHEJ7a9KAGGdXEkQIAAHABIeJGaD4BABABKVpKHwAAAAAAURrmlQ1oJIIzYMbA9KAG"]}],["gameactivity",{"version":4,"data":["EMTOjaIGGAIgAygBMAE4AVDxBVgGYO2lpIBeagEA","EPeg96AGGAIgASgCMAZQ8QVYBmDFz8PbXGoBAA==","EMuE96AGGAIgASgCMBRQ8QVYBmDct5TbXGoBAA==","EJ7o9qAGGAIgASgCMAZQ8QVYBmDm3uHaXGoBAA==","ENbL9qAGGAIgASgCMBRQ8QVYBmDZjK3aXGoBAA==","ELGv9qAGGAIgASgCMBNQ8QVYBmCq+f3ZXGoBAA=="]}],["socialmedia",{"version":3,"data":[]}],["associations",{"version":2,"data":{"rgDevelopers":[{"strName":"CAPCOM Co., Ltd.","strURL":null}],"rgPublishers":[{"strName":"CAPCOM Co., Ltd.","strURL":null}],"rgFranchises":[{"strName":"Resident Evil","strURL":"https://store.steampowered.com/curator/34827950"}]}}],["descriptions",{"version":1,"data":{"strFullDescription":"Sobrevivência é apenas o começo.\r\n\r\nSeis anos se passaram desde o desastre biológico em Raccoon City.\r\nO agente Leon S. Kennedy, um dos sobreviventes do incidente, foi enviado para resgatar a filha raptada do presidente.\r\nEle segue o rastro dela até uma isolada vila europeia, onde há algo terrivelmente errado com os habitantes.\r\nEntão a cortina se abre nessa história de um resgate ousado e um terror medonho, onde vida e morte, terror e catarse, se encontram.\r\n\r\nCom jogabilidade modernizada, uma história reimaginada e gráficos com detalhes vívidos,\r\nResident Evil 4 marca o renascimento de um gigante da indústria.\r\n\r\nReviva o pesadelo que revolucionou o terror de sobrevivência.","strSnippet":"Sobrevivência é apenas o começo. Seis anos se passaram desde o desastre biológico em Raccoon City. Leon S. Kennedy, um dos sobreviventes, segue o rastro da raptada filha do presidente até uma vila europeia isolada, onde há algo terrivelmente errado com os habitantes."}}],["community_items",{"version":1,"data":[{"item_type":1,"appid":2050650,"item_name":"test badge","item_title":"test badge","item_description":"","item_image_small":"","item_image_large":"","item_key_values":"{\n\t\"level_images\": {\n\t\t\"1\": \"27a49b5b41a58c3452d253e2346db4363dc98061.png\",\n\t\t\"2\": \"403abb3cec56d1669b2db4e69c83de017a3c1f0a.png\",\n\t\t\"3\": \"d4e87366c8836c3a31bbf86a968ab7c79dd297f9.png\",\n\t\t\"4\": \"1a3239553b0077fac32903895b71ae934b57d67a.png\",\n\t\t\"5\": \"d4fc033145d3577210432b499024ca32f2d284d6.png\",\n\t\t\"foil\": \"5385d3148f0ed222724e70c47c33f9c0c97f86d5.png\"\n\t}\n,\n\t\"level_names\": {\n\t\t\"1\": {\n\t\t\t\"arabic\": \"\",\n\t\t\t\"italian\": \"Rubino\",\n\t\t\t\"ukrainian\": \"\",\n\t\t\t\"dutch\": \"\",\n\t\t\t\"greek\": \"\",\n\t\t\t\"swedish\": \"\",\n\t\t\t\"spanish\": \"Rubí\",\n\t\t\t\"latam\": \"Rubí\",\n\t\t\t\"thai\": \"\",\n\t\t\t\"czech\": \"\",\n\t\t\t\"danish\": \"\",\n\t\t\t\"turkish\": \"\",\n\t\t\t\"german\": \"Rubin\",\n\t\t\t\"norwegian\": \"\",\n\t\t\t\"hungarian\": \"\",\n\t\t\t\"finnish\": \"\",\n\t\t\t\"french\": \"Rubis\",\n\t\t\t\"bulgarian\": \"\",\n\t\t\t\"vietnamese\": \"\",\n\t\t\t\"brazilian\": \"Rubi\",\n\t\t\t\"portuguese\": \"\",\n\t\t\t\"polish\": \"\",\n\t\t\t\"romanian\": \"\",\n\t\t\t\"russian\": \"Рубин\",\n\t\t\t\"schinese\": \"红宝石\",\n\t\t\t\"tchinese\": \"紅寶石\",\n\t\t\t\"japanese\": \"ルビー\",\n\t\t\t\"english\": \"Ruby\",\n\t\t\t\"koreana\": \"루비\"\n\t\t}\n,\n\t\t\"2\": {\n\t\t\t\"arabic\": \"\",\n\t\t\t\"italian\": \"Caraffa\",\n\t\t\t\"ukrainian\": \"\",\n\t\t\t\"dutch\": \"\",\n\t\t\t\"greek\": \"\",\n\t\t\t\"swedish\": \"\",\n\t\t\t\"spanish\": \"Jarra\",\n\t\t\t\"latam\": \"Jarra\",\n\t\t\t\"thai\": \"\",\n\t\t\t\"czech\": \"\",\n\t\t\t\"danish\": \"\",\n\t\t\t\"turkish\": \"\",\n\t\t\t\"german\": \"Weinkanne\",\n\t\t\t\"norwegian\": \"\",\n\t\t\t\"hungarian\": \"\",\n\t\t\t\"finnish\": \"\",\n\t\t\t\"french\": \"Pichet\",\n\t\t\t\"bulgarian\": \"\",\n\t\t\t\"vietnamese\": \"\",\n\t\t\t\"brazilian\": \"Jarro\",\n\t\t\t\"portuguese\": \"\",\n\t\t\t\"polish\": \"\",\n\t\t\t\"romanian\": \"\",\n\t\t\t\"russian\": \"Графин\",\n\t\t\t\"schinese\": \"酒壶\",\n\t\t\t\"tchinese\": \"酒壺\",\n\t\t\t\"japanese\": \"フラゴン\",\n\t\t\t\"english\": \"Flagon\",\n\t\t\t\"koreana\": \"손잡이 달린 호리병\"\n\t\t}\n,\n\t\t\"3\": {\n\t\t\t\"arabic\": \"\",\n\t\t\t\"italian\": \"Maschera elegante\",\n\t\t\t\"ukrainian\": \"\",\n\t\t\t\"dutch\": \"\",\n\t\t\t\"greek\": \"\",\n\t\t\t\"swedish\": \"\",\n\t\t\t\"spanish\": \"Máscara elegante\",\n\t\t\t\"latam\": \"Máscara elegante\",\n\t\t\t\"thai\": \"\",\n\t\t\t\"czech\": \"\",\n\t\t\t\"danish\": \"\",\n\t\t\t\"turkish\": \"\",\n\t\t\t\"german\": \"Elegante Maske\",\n\t\t\t\"norwegian\": \"\",\n\t\t\t\"hungarian\": \"\",\n\t\t\t\"finnish\": \"\",\n\t\t\t\"french\": \"Masque élégant\",\n\t\t\t\"bulgarian\": \"\",\n\t\t\t\"vietnamese\": \"\",\n\t\t\t\"brazilian\": \"Máscara Elegante\",\n\t\t\t\"portuguese\": \"\",\n\t\t\t\"polish\": \"\",\n\t\t\t\"romanian\": \"\",\n\t\t\t\"russian\": \"Элегантная маска\",\n\t\t\t\"schinese\": \"奢华的面具\",\n\t\t\t\"tchinese\": \"高貴面具\",\n\t\t\t\"japanese\": \"くぼみのある仮面\",\n\t\t\t\"english\": \"Elegant Mask\",\n\t\t\t\"koreana\": \"고상한 가면\"\n\t\t}\n,\n\t\t\"4\": {\n\t\t\t\"arabic\": \"\",\n\t\t\t\"italian\": \"Collana barocca\",\n\t\t\t\"ukrainian\": \"\",\n\t\t\t\"dutch\": \"\",\n\t\t\t\"greek\": \"\",\n\t\t\t\"swedish\": \"\",\n\t\t\t\"spanish\": \"Collar ornamentado\",\n\t\t\t\"latam\": \"Collar ornamentado\",\n\t\t\t\"thai\": \"\",\n\t\t\t\"czech\": \"\",\n\t\t\t\"danish\": \"\",\n\t\t\t\"turkish\": \"\",\n\t\t\t\"german\": \"Kunstvolle Halskette\",\n\t\t\t\"norwegian\": \"\",\n\t\t\t\"hungarian\": \"\",\n\t\t\t\"finnish\": \"\",\n\t\t\t\"french\": \"Collier orné\",\n\t\t\t\"bulgarian\": \"\",\n\t\t\t\"vietnamese\": \"\",\n\t\t\t\"brazilian\": \"Colar Adornado\",\n\t\t\t\"portuguese\": \"\",\n\t\t\t\"polish\": \"\",\n\t\t\t\"romanian\": \"\",\n\t\t\t\"russian\": \"Вычурное ожерелье\",\n\t\t\t\"schinese\": \"华贵的项链\",\n\t\t\t\"tchinese\": \"寶石項鍊\",\n\t\t\t\"japanese\": \"宝飾のある首飾り\",\n\t\t\t\"english\": \"Ornate Necklace\",\n\t\t\t\"koreana\": \"장식 달린 목걸이\"\n\t\t}\n,\n\t\t\"5\": {\n\t\t\t\"arabic\": \"\",\n\t\t\t\"italian\": \"Corona elegante\",\n\t\t\t\"ukrainian\": \"\",\n\t\t\t\"dutch\": \"\",\n\t\t\t\"greek\": \"\",\n\t\t\t\"swedish\": \"\",\n\t\t\t\"spanish\": \"Corona elegante\",\n\t\t\t\"latam\": \"Corona elegante\",\n\t\t\t\"thai\": \"\",\n\t\t\t\"czech\": \"\",\n\t\t\t\"danish\": \"\",\n\t\t\t\"turkish\": \"\",\n\t\t\t\"german\": \"Elegante Krone\",\n\t\t\t\"norwegian\": \"\",\n\t\t\t\"hungarian\": \"\",\n\t\t\t\"finnish\": \"\",\n\t\t\t\"french\": \"Couronne\",\n\t\t\t\"bulgarian\": \"\",\n\t\t\t\"vietnamese\": \"\",\n\t\t\t\"brazilian\": \"Coroa Elegante\",\n\t\t\t\"portuguese\": \"\",\n\t\t\t\"polish\": \"\",\n\t\t\t\"romanian\": \"\",\n\t\t\t\"russian\": \"Элегантная корона\",\n\t\t\t\"schinese\": \"高贵的王冠\",\n\t\t\t\"tchinese\": \"高貴王冠\",\n\t\t\t\"japanese\": \"くぼみのある宝冠\",\n\t\t\t\"english\": \"Elegant Crown\",\n\t\t\t\"koreana\": \"고상한 왕관\"\n\t\t}\n,\n\t\t\"foil\": {\n\t\t\t\"arabic\": \"\",\n\t\t\t\"italian\": \"Castellano meccanico\",\n\t\t\t\"ukrainian\": \"\",\n\t\t\t\"dutch\": \"\",\n\t\t\t\"greek\": \"\",\n\t\t\t\"swedish\": \"\",\n\t\t\t\"spanish\": \"Castellano mecánico\",\n\t\t\t\"latam\": \"Castellano mecánico\",\n\t\t\t\"thai\": \"\",\n\t\t\t\"czech\": \"\",\n\t\t\t\"danish\": \"\",\n\t\t\t\"turkish\": \"\",\n\t\t\t\"german\": \"Aufzieh-Kastellan\",\n\t\t\t\"norwegian\": \"\",\n\t\t\t\"hungarian\": \"\",\n\t\t\t\"finnish\": \"\",\n\t\t\t\"french\": \"Châtelain mécanique\",\n\t\t\t\"bulgarian\": \"\",\n\t\t\t\"vietnamese\": \"\",\n\t\t\t\"brazilian\": \"Castelão Mecânico\",\n\t\t\t\"portuguese\": \"\",\n\t\t\t\"polish\": \"\",\n\t\t\t\"romanian\": \"\",\n\t\t\t\"russian\": \"Заводной смотритель\",\n\t\t\t\"schinese\": \"城主人偶\",\n\t\t\t\"tchinese\": \"城主人偶\",\n\t\t\t\"japanese\": \"貴族人形\",\n\t\t\t\"english\": \"Clockwork Castellan\",\n\t\t\t\"koreana\": \"태엽식 귀족 인형\"\n\t\t}\n\n\t}\n\n}\n","item_series":1,"item_class":1,"active":true,"item_last_changed":1679500382,"item_movie_webm":"","item_movie_mp4":"","item_movie_webm_small":"","item_movie_mp4_small":""},{"item_type":6,"appid":2050650,"item_name":"Leon S. Kennedy","item_title":"Leon S. Kennedy","item_description":"Um dos poucos sobreviventes do Incidente em Raccoon City, ele continuou aperfeiçoando suas capacidades como agente de um programa secreto do governo dos Estados Unidos. Sua missão mais recente o levou a um vilarejo isolado na Europa em busca de Ashley Graham, a filha desaparecida do presidente.","item_image_small":"b47a4cdf46238ff368470a228f3d98e23d993aea.png","item_image_large":"5a011883b3eb9f28a52743c0b795a0d72c3e9ad7.jpg","item_series":1,"item_class":2,"active":true,"item_image_composed":"IzMF03bk9WpSBq-S-ekoE33L-iLqGFHVaU25ZzQNQcXdA3g5gMEPvUZZEfSLO6FSSMAouGvDXJfBjI0CxnMJmDgDemTs1GBhYLhAPcTIiza16smIEnrybC6CJizYG1s1H7dZZGyKqmWh4--XSm6fQu4kRw4ELKAG-jJKacCBahA-gI4C-GS9lgptEBFucMpUdAqp9X0eMLoglSNBJJ4EyiX1JJOKjVs3OUE5Xb7iBejBO4ijlistDh9mHadLMdmQvXDyuMmmfLGLL0FqM9N8","item_image_composed_foil":"IzMF03bk9WpSBq-S-ekoE33L-iLqGFHVaU25ZzQNQcXdA3g5gMEPvUZZEfSLO6FSSMAouGvDXJfBjI0CxnMJmDgDemTs1GBhYLhAPcTIiza16smIEnrybC6CJizYG1s1H7dZZGyKqmWh4--XSm6fQu4kRw4ELKAG-jJKacCBahA-gI4C-GS9lgptEBFucMpUdAqp9X0eMLoglSMUc51WmXL0L5HbjVo0bRI7U72yVO7EbND3kCp1X05gTfMeNYrG7ifyuMmmfLGLL1A9OlzW","item_last_changed":1674438020,"item_movie_webm":"","item_movie_mp4":"","item_movie_webm_small":"","item_movie_mp4_small":""},{"item_type":12,"appid":2050650,"item_name":"Ashley Graham","item_title":"Ashley Graham","item_description":"Universitária e adorada filha do presidente dos Estados Unidos. Desaparecida no momento. Sua ausência repentina acabou revelando-se um sequestro, e as buscas por ela continuam a todo vapor.","item_image_small":"5a38db6d4c1a510551a87988fb7e5b6690b8f566.png","item_image_large":"7ba126a6d91c12dacef61c9819de7e71f8fb881a.jpg","item_series":1,"item_class":2,"active":true,"item_image_composed":"IzMF03bk9WpSBq-S-ekoE33L-iLqGFHVaU25ZzQNQcXdA3g5gMEPvUZZEfSLO6FSSMAouGvDXJfBjI0CxnMJmDgDemTs1GBhYLhNK8PKxRywhvCMFHX6Lj7JLibcQQtpTrsKZ26N-mCktOiVQj3MQLkkRAAMdfRW9TFMb8-PNhJv3NEO_TP2h0p6WBQnYMFDYjCyx3UUNOAnmyBHI8hTnCb3dZzd0A5lO0FsX-uzVejLaYehmXwhXBhgTvVIYY7ApmWyr4G3Z_UfW1Nyyw","item_image_composed_foil":"IzMF03bk9WpSBq-S-ekoE33L-iLqGFHVaU25ZzQNQcXdA3g5gMEPvUZZEfSLO6FSSMAouGvDXJfBjI0CxnMJmDgDemTs1GBhYLhNK8PKxRywhvCMFHX6Lj7JLibcQQtpTrsKZ26N-mCktOiVQj3MQLkkRAAMdfRW9TFMb8-PNhJv3NEO_TP2h0p6WBQnYMFDYjCyx3UUNOAnzndEcZsEnS31JJzc01o2OU9vD7q1UL-TPYGgwS1wWkg0G_EbN92XpmWyr4G3Z_VizdofaA","item_last_changed":1674438059,"item_movie_webm":"","item_movie_mp4":"","item_movie_webm_small":"","item_movie_mp4_small":""},{"item_type":13,"appid":2050650,"item_name":"Luis Serra Navarro","item_title":"Luis Serra Navarro","item_description":"A person of interest that Leon encounters during his search for Ashley. Underneath his flippant personality lies some sort of ulterior motive.","item_image_small":"e188ae795409c881125336708a03178798e86718.png","item_image_large":"45fae86dfa091283b8a07b2a6a74d6951716387a.jpg","item_series":1,"item_class":2,"active":true,"item_image_composed":"IzMF03bk9WpSBq-S-ekoE33L-iLqGFHVaU25ZzQNQcXdA3g5gMEPvUZZEfSMJ6dESN8p_2SVTY7V2NsPwXMKnT4QPivs0XEwSfBlK4D1xRfpoKmjHWL2eiXLaSjUHVltQOZfPWCIqzSs4OmUS2vBSektQQwHfqQD8mwYPcqIOBo63Y9e8zPvxhwzDhgvNMdJYgu-2EsaPLwizXwQdspXz3fxI5be1ldmPRdtCb_hU--WbNWslikgVEliHqIdNd7HvSC55tevPeHAIPrO-PvDKQ","item_image_composed_foil":"IzMF03bk9WpSBq-S-ekoE33L-iLqGFHVaU25ZzQNQcXdA3g5gMEPvUZZEfSMJ6dESN8p_2SVTY7V2NsPwXMKnT4QPivs0XEwSfBlK4D1xRfpoKmjHWL2eiXLaSjUHVltQOZfPWCIqzSs4OmUS2vBSektQQwHfqQD8mwYPcqIOBo63Y9e8zPvxhwzDhgvNMdJYgu-2EsaPLwizXwQI51UnSSmIp3ch1dnPkM-C7HiA76QaYL0wi8hDBgzGPJJYNqU63Pu5tevPeHAIPqR0dERdw","item_last_changed":1674438096,"item_movie_webm":"","item_movie_mp4":"","item_movie_webm_small":"","item_movie_mp4_small":""},{"item_type":14,"appid":2050650,"item_name":"Ada Wong","item_title":"Ada Wong","item_description":"Uma mulher enigmática que parece ter seu destino entrelaçado ao de Leon. Havia sido considerada morta após os acontecimentos do Incidente em Raccoon City.","item_image_small":"a0a3d185b202aa708fc6c59eb9d3fa7d2789db7f.png","item_image_large":"c67fad9e55142c1cd0a16d7347f88cebbfc578d8.jpg","item_series":1,"item_class":2,"active":true,"item_image_composed":"IzMF03bk9WpSBq-S-ekoE33L-iLqGFHVaU25ZzQNQcXdA3g5gMEPvUZZEfSLO6FSSMAouGvDXJfBjI0CxnMJmDgDemTs1GBhYLhNPMqN9wr1pqSEEXXwbWrFfyCKGA8wSOFcNWqIrzSl7bvHRGvMSL1-Sl0HK_MDpmZONcDdbRVrysdVrCO6mFZ5GwQXe8hHdwrmyCcSZLsmmXRAcshanXGhIcfeg1oxPEU-U77hUrWRaoCnl35xDx9iSr5aOtyD_ijuhgCaBS4","item_image_composed_foil":"IzMF03bk9WpSBq-S-ekoE33L-iLqGFHVaU25ZzQNQcXdA3g5gMEPvUZZEfSLO6FSSMAouGvDXJfBjI0CxnMJmDgDemTs1GBhYLhNPMqN9wr1pqSEEXXwbWrFfyCKGA8wSOFcNWqIrzSl7bvHRGvMSL1-Sl0HK_MDpmZONcDdbRVrysdVrCO6mFZ5GwQXe8hHdwrmyHJFZ-l1znVLcJlanHL1csXQgApgOkBpC-rnU-3AO4b3wyt1XEkxHb5aOtyD_ijuHbPqUyQ","item_last_changed":1674438245,"item_movie_webm":"","item_movie_mp4":"","item_movie_webm_small":"","item_movie_mp4_small":""},{"item_type":15,"appid":2050650,"item_name":"Ingrid Hunnigan","item_title":"Ingrid Hunnigan","item_description":"Uma coordenadora de missões que pertence à mesma organização governamental que Leon. Sempre profissional, nunca perde a compostura sob pressão e ajuda Leon pelo rádio.","item_image_small":"ef0c19f4e79c89e38836bef41d4517eee104f465.png","item_image_large":"0f6629d51cbd3ab61dcf0e5c3850efbb5815a9b9.jpg","item_series":1,"item_class":2,"active":true,"item_image_composed":"IzMF03bk9WpSBq-S-ekoE33L-iLqGFHVaU25ZzQNQcXdA3g5gMEPvUZZEfSLO6FSSMAouGvDXJfBjI0CxnMJmDgDemTs1GBhYLhFNszUyQGwifeDEn3waTmCJizYG1s1GOVeZmnQqDfw4uTHSjGcQuAkQA9WKPQA8zBNOMiOakdo1YcPrTHuwgptEBFucMpUdAqp9X0eMLoglSNBJJ4EyiX1JJOKjVs3OUE5Xb7iBejBO4ijlistDh9mHadLMdmQvXDyuMmmfLGLL0i3Kl75","item_image_composed_foil":"IzMF03bk9WpSBq-S-ekoE33L-iLqGFHVaU25ZzQNQcXdA3g5gMEPvUZZEfSLO6FSSMAouGvDXJfBjI0CxnMJmDgDemTs1GBhYLhFNszUyQGwifeDEn3waTmCJizYG1s1GOVeZmnQqDfw4uTHSjGcQuAkQA9WKPQA8zBNOMiOakdo1YcPrTHuwgptEBFucMpUdAqp9X0eMLoglSMUc51WmXL0L5HbjVo0bRI7U72yVO7EbND3kCp1X05gTfMeNYrG7ifyuMmmfLGLL5Fs7MgN","item_last_changed":1674438709,"item_movie_webm":"","item_movie_mp4":"","item_movie_webm_small":"","item_movie_mp4_small":""},{"item_type":16,"appid":2050650,"item_name":"Merchant","item_title":"Mercador","item_description":"Um mercador de armas que aparece em diversos locais da região. Embora ele esteja felicíssimo em negociar produtos com Leon, suas reais motivações permanecem um mistério.","item_image_small":"67a6fbddd975610a31062c0fdb32acf8e5f5e05d.png","item_image_large":"90dd7c0d2b3180954cb9d1e1e3e359e5abdb571c.jpg","item_series":1,"item_class":2,"active":true,"item_image_composed":"IzMF03bk9WpSBq-S-ekoE33L-iLqGFHVaU25ZzQNQcXdA3g5gMEPvUZZEfSLO6FSSMAouGvDXJfBjI0CxnMJmDgDemTs1GBhYLhBPdnFwQH0s6SEEXXwbWqSeCCPGlxsGedXMm3f_zP05uyURDqaQb54EQoGLPFS-jFMa8zcPxdpysdVrCO6mFZ5GwQXe8hHdwrmyCcSZLsmmXRAcshanXGhIcfeg1oxPEU-U77hUrWRaoCnl35xDx9iSr5aOtyD_ijulhX4PXU","item_image_composed_foil":"IzMF03bk9WpSBq-S-ekoE33L-iLqGFHVaU25ZzQNQcXdA3g5gMEPvUZZEfSLO6FSSMAouGvDXJfBjI0CxnMJmDgDemTs1GBhYLhBPdnFwQH0s6SEEXXwbWqSeCCPGlxsGedXMm3f_zP05uyURDqaQb54EQoGLPFS-jFMa8zcPxdpysdVrCO6mFZ5GwQXe8hHdwrmyHJFZ-l1znVLcJlanHL1csXQgApgOkBpC-rnU-3AO4b3wyt1XEkxHb5aOtyD_ijuOp3PF80","item_last_changed":1674439293,"item_movie_webm":"","item_movie_mp4":"","item_movie_webm_small":"","item_movie_mp4_small":""},{"item_type":17,"appid":2050650,"item_name":"Bitores Méndez","item_title":"Bitores Méndez","item_description":"Um homem com um porte físico imponente que parece imune a dano de armas de fogo. Implacável em sua perseguição a Ashley e em seus esforços para impedir que Leon a salve.","item_image_small":"8e25774c09ad16f9fd2451cd2c05f27af0117837.png","item_image_large":"f783357538eef3a6ab2fd02b2fc0e49f9c638598.jpg","item_series":1,"item_class":2,"active":true,"item_image_composed":"IzMF03bk9WpSBq-S-ekoE33L-iLqGFHVaU25ZzQNQcXdA3g5gMEPvUZZEfSLO6FSSMAouGvDXJfBjI0CxnMJmDgDemTs1GBhYLhOMd_J0gDo6s_IPyeySW7KKyTDWldlHOQLOGCM_Dai4unHQjGYFekqFQBSKaAA92UaacvaPxdr1oBarTXpxhMlTUFmYstBNg202HAWI4IsxSAVIJYAmnX1cMfYgF1lO05uD-ngBbvEatLxk3stWxxjFvMfZYmS6XC-_ZKkdLfYeu5xafMOV9WzRw","item_image_composed_foil":"IzMF03bk9WpSBq-S-ekoE33L-iLqGFHVaU25ZzQNQcXdA3g5gMEPvUZZEfSLO6FSSMAouGvDXJfBjI0CxnMJmDgDemTs1GBhYLhOMd_J0gDo6s_IPyeySW7KKyTDWldlHOQLOGCM_Dai4unHQjGYFekqFQBSKaAA92UaacvaPxdr1oBarTXpxhMlTUFmYstBNg202HAWI4IsxSAVIJYAzyL2IpSPgVZnak5vDL2zB7XHOoP3lix1DxpiTqJOY9nGvHTtq8HzdLfYeu5xafO4GU6aZw","item_last_changed":1674442822,"item_movie_webm":"","item_movie_mp4":"","item_movie_webm_small":"","item_movie_mp4_small":""},{"item_type":18,"appid":2050650,"item_name":"Ramón Salazar","item_title":"Ramón Salazar","item_description":"O soberano perverso do castelo da região. Sua adoração fanática por seu mestre é responsável por diversos esquemas aterrorizantes para Leon e Ashley.","item_image_small":"bd434be19262cd0d6cb1344bad3570978ce1fc88.png","item_image_large":"592d0fb12ef518a97f2245d60564f76585b342b1.jpg","item_series":1,"item_class":2,"active":true,"item_image_composed":"IzMF03bk9WpSBq-S-ekoE33L-iLqGFHVaU25ZzQNQcXdA3g5gMEPvUZZEfSLO6FSSMAouGvDXJfBjI0CxnMJmDgDemTs1GBhYLheOcaD41a-g7GDV0f2ZDbeLjOfFVNpGuZTZzzd_Tf3sOydQD7LErwsFw9XL6MH9mAbbJ2KOhU93YADqGDpkUclRlg4fMIAcgCpznEBDrQoySYXeMlRyCGmdZXch1gxYEI_C7-0UbrHPNWmxCYiWx5uTKUbZozE7Xfp_cLvKqnRO746Zvcv3XoN","item_image_composed_foil":"IzMF03bk9WpSBq-S-ekoE33L-iLqGFHVaU25ZzQNQcXdA3g5gMEPvUZZEfSLO6FSSMAouGvDXJfBjI0CxnMJmDgDemTs1GBhYLheOcaD41a-g7GDV0f2ZDbeLjOfFVNpGuZTZzzd_Tf3sOydQD7LErwsFw9XL6MH9mAbbJ2KOhU93YADqGDpkUclRlg4fMIAcgCpznEBDrQoySYXeMkEnyL0JsLdjFpgYEM8X-y2X7mXbdOjk352XR82HfQdNtiR6SS_rpXvKqnRO746ZtnrNe8H","item_last_changed":1674442859,"item_movie_webm":"","item_movie_mp4":"","item_movie_webm_small":"","item_movie_mp4_small":""},{"item_type":19,"appid":2050650,"item_name":"Jack Krauser","item_title":"Jack Krauser","item_description":"O mentor de Leon nos seus tempos de agente em treinamento. Era um soldado prestigiado, mas agora trabalha para um culto abominável.","item_image_small":"64a4e752e4f81b4554b161fc1254718e2d484961.png","item_image_large":"5e0d62fceb0605e9b31dc696333ffc2fc6286e9b.jpg","item_series":1,"item_class":2,"active":true,"item_image_composed":"IzMF03bk9WpSBq-S-ekoE33L-iLqGFHVaU25ZzQNQcXdA3g5gMEPvUZZEfSLO6FSSMAouGvDXJfBjI0CxnMJmDgDemTs1GBhYLhGOcjNiy7poPeeGWaxYTrFKCSESgppSeZZMGqM-mWt5L-QRz3NE-kqQl9XfKAB9mNINZyLaxY10I4N-iuomUM7HBk6dsBUTwa2y3MWbL92yXQUJppXmyOjLpCM1Fgxb0BvCezkArXEaYWswyolXx02SvIfYd6L-Hu77tH8aOfF7Ml-","item_image_composed_foil":"IzMF03bk9WpSBq-S-ekoE33L-iLqGFHVaU25ZzQNQcXdA3g5gMEPvUZZEfSLO6FSSMAouGvDXJfBjI0CxnMJmDgDemTs1GBhYLhGOcjNiy7poPeeGWaxYTrFKCSESgppSeZZMGqM-mWt5L-QRz3NE-kqQl9XfKAB9mNINZyLaxY10I4N-iuomUM7HBk6dsBUTwa2y3MWbL8jnndGdc1WkCHyLpGPgAszYUM_WOrhVe2Qb4T0knsjD0ljTqFJMomL-Hu77tH8aH621yT2","item_last_changed":1674449455,"item_movie_webm":"","item_movie_mp4":"","item_movie_webm_small":"","item_movie_mp4_small":""},{"item_type":20,"appid":2050650,"item_name":"Osmund Saddler","item_title":"Osmund Saddler","item_description":"O líder de Los Iluminados. Portador de um poder sobrenatural que permite controlar seus inúmeros discípulos.","item_image_small":"ec2804c4c2ae0ec6a9abde6fcf888adcf49039c7.png","item_image_large":"9e885fab1503b5ea0ce6b896ad1972e41164d213.jpg","item_series":1,"item_class":2,"active":true,"item_image_composed":"IzMF03bk9WpSBq-S-ekoE33L-iLqGFHVaU25ZzQNQcXdA3g5gMEPvUZZEfSLO6FSSMAouGvDXJfBjI0CxnMJmDgDemTs1GBhYLhDK8bTzgGwkuOJGHjyenHNIiDeGQNtHrFWNWyK-mCntLiUF2vPEOF9EV1Re_RXpGxBNZjdbEQ53YcI8mbv2VRzGVAqfddCdR2Ew3kSNrh4ynITcM0BmCHyIcfRgQozbxVtXL20Ar-WZoejlCZ3WBtlGPFPNo6Q7TuspsDnLPqEfSv1b_I","item_image_composed_foil":"IzMF03bk9WpSBq-S-ekoE33L-iLqGFHVaU25ZzQNQcXdA3g5gMEPvUZZEfSLO6FSSMAouGvDXJfBjI0CxnMJmDgDemTs1GBhYLhDK8bTzgGwkuOJGHjyenHNIiDeGQNtHrFWNWyK-mCntLiUF2vPEOF9EV1Re_RXpGxBNZjdbEQ53YcI8mbv2VRzGVAqfddCdR2Ew3kSNrh4yidEc59SzyD5I5bRgAlnPBdjX-3lBLrBPtOllX4mCR01TKRLZdjDujuspsDnLPqEWwS4dxs","item_last_changed":1674449495,"item_movie_webm":"","item_movie_mp4":"","item_movie_webm_small":"","item_movie_mp4_small":""},{"item_type":25,"appid":2050650,"item_name":"Booster Pack","item_title":"Booster Pack","item_description":"","item_image_small":"","item_image_large":"","item_series":1,"item_class":5,"active":true,"item_image_composed":"IzMF03bk9WpSBq-S-ekoE33L-iLqGFHVaU25ZzQNQcXdBnY7ltYLvVIHHqLGe_AdEZp06TqJAIXDhJNWmCpdxihFIzj9gGdgZOlgzSZ2hJ4","item_last_changed":1679620267,"item_movie_webm":"","item_movie_mp4":"","item_movie_webm_small":"","item_movie_mp4_small":""}]}]]