[["achievements",{"version":2,"data":{"vecHighlight":[],"vecUnachieved":[{"strID":"Achievement14","strName":"El primer bocado de caos","strDescription":"Sembrar el caos por primera vez.","strImage":"https://steamcdn-a.akamaihd.net/steamcommunity/public/images/apps/8190/23bd4d0e1fc4dfd452aa699ab3bb93351a4ddb87.jpg","bAchieved":false,"rtUnlocked":0,"flAchieved":86.9000015258789,"flMinProgress":0,"flCurrentProgress":0,"flMaxProgress":0},{"strID":"Achievement1","strName":"Bienvenido a Panau","strDescription":"Completar misión de agencia 1.","strImage":"https://steamcdn-a.akamaihd.net/steamcommunity/public/images/apps/8190/24560ca3d14d54eeaff2eaea85963827b78d24f6.jpg","bAchieved":false,"rtUnlocked":0,"flAchieved":76.9000015258789,"flMinProgress":0,"flCurrentProgress":0,"flMaxProgress":0},{"strID":"Achievement2","strName":"Redada en el casino","strDescription":"Completar misión de agencia 2.","strImage":"https://steamcdn-a.akamaihd.net/steamcommunity/public/images/apps/8190/a1bca11cfd8bafb2463a7105246223662170ea19.jpg","bAchieved":false,"rtUnlocked":0,"flAchieved":65,"flMinProgress":0,"flCurrentProgress":0,"flMaxProgress":0},{"strID":"Achievement38","strName":"Frenesí de destrucción","strDescription":"Destruir 30 objetos en 60 segundos.","strImage":"https://steamcdn-a.akamaihd.net/steamcommunity/public/images/apps/8190/893658f02058326812417b1d253e57e83690547c.jpg","bAchieved":false,"rtUnlocked":0,"flAchieved":60.599998474121094,"flMinProgress":0,"flCurrentProgress":0,"flMaxProgress":0},{"strID":"Achievement39","strName":"Conductor de pruebas","strDescription":"Conducir 30 vehículos diferentes.","strImage":"https://steamcdn-a.akamaihd.net/steamcommunity/public/images/apps/8190/cea40da368123c78f06013765a649f269964c88b.jpg","bAchieved":false,"rtUnlocked":0,"flAchieved":34.900001525878906,"flMinProgress":0,"flCurrentProgress":0,"flMaxProgress":0},{"strID":"Achievement11","strName":"Ganar un punto de apoyo","strDescription":"Completar 3 tomas de fortaleza.","strImage":"https://steamcdn-a.akamaihd.net/steamcommunity/public/images/apps/8190/58a57d43277ff3807237d6a59633a165c9f7edd2.jpg","bAchieved":false,"rtUnlocked":0,"flAchieved":31.899999618530273,"flMinProgress":0,"flCurrentProgress":0,"flMaxProgress":0},{"strID":"Achievement35","strName":"Tirador","strDescription":"Matar a 50 enemigos con tiros en la cabeza.","strImage":"https://steamcdn-a.akamaihd.net/steamcommunity/public/images/apps/8190/38776aaf9aef4311f53ae07922bf44148a905f32.jpg","bAchieved":false,"rtUnlocked":0,"flAchieved":30.899999618530273,"flMinProgress":0,"flCurrentProgress":0,"flMaxProgress":0},{"strID":"Achievement21","strName":"Lo que se da no se quita","strDescription":"Recoger 100 elementos de recursos.","strImage":"https://steamcdn-a.akamaihd.net/steamcommunity/public/images/apps/8190/df0053562c64690d846f037d0f8f5b95f7557475.jpg","bAchieved":false,"rtUnlocked":0,"flAchieved":28,"flMinProgress":0,"flCurrentProgress":0,"flMaxProgress":0},{"strID":"Achievement3","strName":"El Tigre blanco","strDescription":"Completar misión de agencia 3.","strImage":"https://steamcdn-a.akamaihd.net/steamcommunity/public/images/apps/8190/8cda3c956eebaf4980be7366f7f9310388addb54.jpg","bAchieved":false,"rtUnlocked":0,"flAchieved":27.5,"flMinProgress":0,"flCurrentProgress":0,"flMaxProgress":0},{"strID":"Achievement15","strName":"Saboteador","strDescription":"Completar 150 sabotajes.","strImage":"https://steamcdn-a.akamaihd.net/steamcommunity/public/images/apps/8190/309d922c2e80a1340b278148a7bf61a7320f9703.jpg","bAchieved":false,"rtUnlocked":0,"flAchieved":27.100000381469727,"flMinProgress":0,"flCurrentProgress":0,"flMaxProgress":0},{"strID":"Achievement41","strName":"Viaje por carretera","strDescription":"Viajar 75 kilómetros en vehículo terrestre.","strImage":"https://steamcdn-a.akamaihd.net/steamcommunity/public/images/apps/8190/5150d3066a60b1a37c206c4e4e23cfabe640e889.jpg","bAchieved":false,"rtUnlocked":0,"flAchieved":25.700000762939453,"flMinProgress":0,"flCurrentProgress":0,"flMaxProgress":0},{"strID":"Achievement26","strName":"Recuento de bajas","strDescription":"Matar 750 enemigos.","strImage":"https://steamcdn-a.akamaihd.net/steamcommunity/public/images/apps/8190/843229f687676d076e668137f481e605dd0ea60b.jpg","bAchieved":false,"rtUnlocked":0,"flAchieved":24.299999237060547,"flMinProgress":0,"flCurrentProgress":0,"flMaxProgress":0}],"vecAchievedHidden":[],"nTotal":50,"nAchieved":0}}]]